azcam_arc/__init__.py
azcam_arc/camera_server.py
azcam_arc/console_arc.py
azcam_arc/controller_arc.py
azcam_arc/exposure_arc.py
azcam_arc/receive_data.py
azcam_arc/tempcon_arc.py
azcam_arc-22.3.3.dist-info/LICENSE
azcam_arc-22.3.3.dist-info/WHEEL
azcam_arc-22.3.3.dist-info/METADATA
azcam_arc-22.3.3.dist-info/RECORD
