Metadata-Version: 2.1
Name: azcam-arc
Version: 22.3.3
Summary: Azcam extension for Astronomical Research Cameras (ARC) gen1, gen2, and gen3 controllers
Keywords: ccd,imaging,astronomy,sensors
Author: Michael Lesser
Author-email: mlesser@arizona.edu
Requires-Dist: azcam
Project-URL: Documentation, https://mplesser.github.io/azcam/
Project-URL: Repository, https://github.com/mplesser/azcam-arc/
